weatherstack/__init__.py
weatherstack/client.py
weatherstack/enums.py
weatherstack/exceptions.py
weatherstack/models.py
weatherstack-0.1.0.dist-info/WHEEL
weatherstack-0.1.0.dist-info/METADATA
weatherstack-0.1.0.dist-info/RECORD
