Metadata-Version: 2.1
Name: weatherstack
Version: 0.1.0
Summary: A Python wrapper around WeatherStack APIs
Author: Morgan Kilgore
Author-email: mkilgore301@gmail.com
Requires-Python: >=3.7,<4.0
Classifier: Programming Language :: Python :: 3
Classifier: Programming Language :: Python :: 3.7
Classifier: Programming Language :: Python :: 3.8
Classifier: Programming Language :: Python :: 3.9
Requires-Dist: pydantic (>=1.7.2,<2.0.0)
Requires-Dist: requests (>=2.25.0,<3.0.0)
